bbrowserx_connector/__init__.py
bbrowserx_connector/_api.py
bbrowserx_connector/_connector.py
bbrowserx_connector/_constants.py
bbrowserx_connector/_submit_format.py
bbrowserx_connector/_utils.py
bbrowserx_connector-1.0.0.dist-info/METADATA
bbrowserx_connector-1.0.0.dist-info/WHEEL
bbrowserx_connector-1.0.0.dist-info/top_level.txt
bbrowserx_connector-1.0.0.dist-info/RECORD
