Metadata-Version: 2.1
Name: bbrowserx-connector
Version: 1.0.0
Summary: BioTuring BBrowserX Connector
Home-page: https://alpha.bioturing.com
Author: BioTuring
Author-email: support@bioturing.com
License: UNKNOWN
Platform: UNKNOWN
Requires-Dist: pydantic (==2.7.2)
Requires-Dist: requests (==2.32.3)
Requires-Dist: tqdm (==4.66.4)
